jupyterlab_slurm/__init__.py
jupyterlab_slurm/slurm.py
jupyterlab_slurm-1.0.5.data/data/etc/jupyter/jupyter_notebook_config.d/jupyterlab_slurm.json
jupyterlab_slurm-1.0.5.dist-info/LICENSE
jupyterlab_slurm-1.0.5.dist-info/METADATA
jupyterlab_slurm-1.0.5.dist-info/WHEEL
jupyterlab_slurm-1.0.5.dist-info/top_level.txt
jupyterlab_slurm-1.0.5.dist-info/RECORD
