Metadata-Version: 2.1
Name: jupyterlab-slurm
Version: 1.0.5
Summary: A Jupyter Notebook server extension that implements common Slurm commands.
Home-page: https://github.com/NERSC/jupyterlab-slurm
Author: NERSC, Jon Hays, William Krinsman
License: BSD 3-Clause
Keywords: Jupyter,Jupyterlab,Slurm,NERSC
Platform: UNKNOWN
Requires-Python: >=3.6
Requires-Dist: notebook
